ulidantic/__init__.py
ulidantic-1.0.0.dist-info/METADATA
ulidantic-1.0.0.dist-info/WHEEL
ulidantic-1.0.0.dist-info/RECORD
