Metadata-Version: 2.1
Name: ulidantic
Version: 1.0.0
Summary: 
Author: Nutchanon Ninyawee
Author-email: nutchanon@codustry.com
Requires-Python: >=3.10,<4.0
Classifier: Programming Language :: Python :: 3
Classifier: Programming Language :: Python :: 3.10
Classifier: Programming Language :: Python :: 3.11
Requires-Dist: pydantic (>=1.10.7,<2.0.0)
Requires-Dist: python-ulid (>=1.1.0,<2.0.0)
